spatialdiva/.empty
spatialdiva/__init__.py
spatialdiva/api/__init__.py
spatialdiva/api/st_diva_api.py
spatialdiva/models/__init__.py
spatialdiva/models/diva_spatial.py
spatialdiva/preprocessing/README.md
spatialdiva/preprocessing/requirements.txt
spatialdiva/preprocessing/scripts/hest1k_uni_feature_extract_and_append.py
spatialdiva/preprocessing/scripts/hest_spot_align_process.py
spatialdiva/preprocessing/src/utils/__init__.py
spatialdiva/preprocessing/src/utils/uni_feature_extract.py
spatialdiva/tutorials/01_colorectal_cancer_spdiva_analysis.ipynb
spatialdiva/utils/__init__.py
spatialdiva/utils/classify.py
spatialdiva/utils/diva_data.py
spatialdiva-0.1b1.dist-info/LICENSE
spatialdiva-0.1b1.dist-info/LICENSE.md
spatialdiva-0.1b1.dist-info/METADATA
spatialdiva-0.1b1.dist-info/WHEEL
spatialdiva-0.1b1.dist-info/RECORD
